pybarnes/__init__.py
pybarnes/barnes_filter.py
pybarnes-0.2.0.dist-info/METADATA
pybarnes-0.2.0.dist-info/WHEEL
pybarnes-0.2.0.dist-info/top_level.txt
pybarnes-0.2.0.dist-info/RECORD
