Metadata-Version: 2.1
Name: pybarnes
Version: 0.2.0
Author: Lin Ouyang
Requires-Dist: metpy
Requires-Dist: tqdm
Requires-Dist: psutil
